pytorreq.py
pytorreq-0.2.6.dist-info/METADATA
pytorreq-0.2.6.dist-info/WHEEL
pytorreq-0.2.6.dist-info/top_level.txt
pytorreq-0.2.6.dist-info/RECORD
