Metadata-Version: 2.1
Name: pytorreq
Version: 0.2.6
Summary: A simple python library that allows you to forward requests through the tor network
Home-page: https://github.com/Exordio/pyTorReq
Author: Ivan Golubev
Author-email: exordio@gmail.com
License: MIT
Platform: UNKNOWN
Requires-Dist: PySocks (>=1.5.7)
Requires-Dist: requests (>=2.25.1)
Requires-Dist: stem (>=1.8.0)
